loom/__init__.py
loom/_revision.py
loom/cliffordsim/__init__.py
loom/cliffordsim/classicalreg.py
loom/cliffordsim/data_store.py
loom/cliffordsim/engine.py
loom/cliffordsim/exceptions.py
loom/cliffordsim/invoker.py
loom/cliffordsim/moment_queue.py
loom/cliffordsim/moments/__init__.py
loom/cliffordsim/moments/base_moment.py
loom/cliffordsim/moments/big_moment.py
loom/cliffordsim/moments/instruction.py
loom/cliffordsim/operations/__init__.py
loom/cliffordsim/operations/base_operation.py
loom/cliffordsim/operations/classical_operation.py
loom/cliffordsim/operations/controlled_operation.py
loom/cliffordsim/operations/datamanipulation_operation.py
loom/cliffordsim/operations/gate_operation.py
loom/cliffordsim/operations/measurement_operation.py
loom/cliffordsim/operations/resize_operation.py
loom/cliffordsim/pauli_frame.py
loom/cliffordsim/tableau.py
loom/eka/__init__.py
loom/eka/block.py
loom/eka/channel.py
loom/eka/circuit.py
loom/eka/circuit_algorithms.py
loom/eka/eka.py
loom/eka/ifelse_circuit.py
loom/eka/lattice.py
loom/eka/logical_state.py
loom/eka/matrices.py
loom/eka/operations/__init__.py
loom/eka/operations/base_operation.py
loom/eka/operations/code_operation.py
loom/eka/operations/logical_measurement.py
loom/eka/operations/logical_operation.py
loom/eka/pauli_operator.py
loom/eka/stabilizer.py
loom/eka/syndrome_circuit.py
loom/eka/tanner_graphs.py
loom/eka/utilities/__init__.py
loom/eka/utilities/enums.py
loom/eka/utilities/exceptions.py
loom/eka/utilities/graph_matrix_utils.py
loom/eka/utilities/logical_operator_finding.py
loom/eka/utilities/pauli_array.py
loom/eka/utilities/pauli_array_computation.py
loom/eka/utilities/pauli_binary_vector_rep.py
loom/eka/utilities/pauli_commutation.py
loom/eka/utilities/pauli_computation.py
loom/eka/utilities/pauli_format_conversion.py
loom/eka/utilities/serialization.py
loom/eka/utilities/stab_array.py
loom/eka/utilities/tableau.py
loom/eka/utilities/validation_tools.py
loom/executor/__init__.py
el_loom-0.4.0.dist-info/METADATA
el_loom-0.4.0.dist-info/WHEEL
el_loom-0.4.0.dist-info/entry_points.txt
el_loom-0.4.0.dist-info/licenses/LICENSE
el_loom-0.4.0.dist-info/RECORD
