Metadata-Version: 2.4
Name: el-loom
Version: 0.4.0
Summary: An integrated software platform designed to handle the complexities of quantum error correction, seamlessly transforming applications into fault-tolerant, hardware-ready versions.
License-File: LICENSE
Author: Entropica Labs Pte Ltd
Author-email: info@entropicalabs.com
Requires-Python: >=3.11,<3.13
Classifier: Programming Language :: Python :: 3
Classifier: Programming Language :: Python :: 3.11
Classifier: Programming Language :: Python :: 3.12
Requires-Dist: igraph (>=0.11.9,<0.12.0)
Requires-Dist: nbformat (>=4.2.0)
Requires-Dist: networkx (>=3.5,<4.0)
Requires-Dist: numpy (>=1.26.0)
Requires-Dist: plotly (>=6.1.2,<6.2.0)
Requires-Dist: pydantic (>=2.9,<2.10)
Requires-Dist: scipy (>=1.16.0,<1.17.0)
Requires-Dist: stim (>=1.14.0,<2.0.0)
